algebraic_immunity-0.1.0.dist-info/METADATA
algebraic_immunity-0.1.0.dist-info/WHEEL
algebraic_immunity/__init__.py
algebraic_immunity/algebraic_immunity.cpython-311-darwin.so
algebraic_immunity-0.1.0.dist-info/RECORD
