Metadata-Version: 2.4
Name: algebraic_immunity
Version: 0.1.0
Classifier: Programming Language :: Rust
Classifier: Programming Language :: Python :: Implementation :: CPython
Classifier: Programming Language :: Python :: Implementation :: PyPy
Summary: A Rust-based Python package to compute the algebraic immunity of Boolean functions.
Home-Page: https://github.com/LucaBonamino/algebraic_immunity
Author: LucaBonamino
Requires-Python: >=3.6
Project-URL: Homepage, https://github.com/LucaBonamino/algebraic_immunity
Project-URL: Repository, https://github.com/LucaBonamino/algebraic_immunity
